awscli_login/__init__.py
awscli_login/__main__.py
awscli_login/_typing.py
awscli_login/_version.py
awscli_login/config.py
awscli_login/configure.py
awscli_login/const.py
awscli_login/credentials.py
awscli_login/exceptions.py
awscli_login/logger.py
awscli_login/saml.py
awscli_login/util.py
awscli_login-1.0.dist-info/LICENSE
awscli_login-1.0.dist-info/METADATA
awscli_login-1.0.dist-info/WHEEL
awscli_login-1.0.dist-info/entry_points.txt
awscli_login-1.0.dist-info/top_level.txt
awscli_login-1.0.dist-info/RECORD
