Metadata-Version: 2.2
Name: awscli-login
Version: 1.0
Summary: Plugin for the AWS CLI that retrieves and rotates credentials using SAML ECP and STS.
Author-email: "David D. Riddle" <ddriddle@illinois.edu>
License: MIT License
Project-URL: Homepage, https://github.com/techservicesillinois/awscli-login
Project-URL: Bug Reports, https://github.com/techservicesillinois/awscli-login/issues
Project-URL: Source, https://github.com/techservicesillinois/awscli-login
Project-URL: Changelog, https://github.com/techservicesillinois/awscli-login/blob/master/CHANGELOG.rst
Keywords: Amazon,AWS,SAML,login,access,keys
Classifier: Development Status :: 5 - Production/Stable
Classifier: Environment :: Console
Classifier: Intended Audience :: Developers
Classifier: Intended Audience :: System Administrators
Classifier: License :: OSI Approved :: MIT License
Classifier: Natural Language :: English
Classifier: Programming Language :: Python :: 3.9
Classifier: Programming Language :: Python :: 3.10
Classifier: Programming Language :: Python :: 3.11
Classifier: Programming Language :: Python :: 3.12
Classifier: Programming Language :: Python :: 3.13
Requires-Python: >=3.9
License-File: LICENSE
Requires-Dist: botocore
Requires-Dist: keyring
Requires-Dist: lxml
Requires-Dist: requests
Provides-Extra: test
Requires-Dist: awscli; extra == "test"
Requires-Dist: tblib; extra == "test"
Requires-Dist: wurlitzer; extra == "test"
Requires-Dist: vcrpy; extra == "test"
